<annotation>
  <filename>tiled_t_1600x900@320x180_2_21-(2).jpg</filename>
  <size>
    <width>320</width>
    <height>180</height>
    <depth>3</depth>
  </size>
  <object>
    <name>great tit</name>
    <bndbox>
      <xmin>60</xmin>
      <ymin>24</ymin>
      <xmax>113</xmax>
      <ymax>51</ymax>
    </bndbox>
  </object>
  <object>
    <name>dunnock</name>
    <bndbox>
      <xmin>217</xmin>
      <ymin>109</ymin>
      <xmax>259</xmax>
      <ymax>163</ymax>
    </bndbox>
  </object>
  <attributes>
    <attribute key="sources">['eb_12_v07\\unclassified\\04-02-53_478-acd007-pi.xml']</attribute>
  </attributes>
</annotation>
