<annotation>
  <folder>goldfinch</folder>
  <filename>14-57-48_102-acd008-pi.jpg</filename>
  <path>X:\nutsack\ground-truth-data\nutsack_11_v8\goldfinch\14-57-48_102-acd008-pi.jpg</path>
  <size>
    <width>1920</width>
    <height>1072</height>
    <depth>3</depth>
  </size>
  <object>
    <name>goldfinch</name>
    <score>0.686965</score>
    <bndbox>
      <xmin>884</xmin>
      <ymin>694</ymin>
      <xmax>1012</xmax>
      <ymax>1067</ymax>
    </bndbox>
    <attributes>
      <attribute key="aspect"></attribute>
      <attribute key="quality">ok</attribute>
      <attribute key="cardinality">1</attribute>
      <attribute key="box-score">97</attribute>
      <attribute key="class-error"></attribute>
      <attribute key="class-error-score">0</attribute>
      <attribute key="class-score">0.0</attribute>
    </attributes>
  </object>
  <attributes>
    <attribute key="weather">cloudy</attribute>
    <attribute key="full-screen">no</attribute>
    <attribute key="quality">ok</attribute>
    <attribute key="duplicate">no</attribute>
    <attribute key="untruth">[]</attribute>
    <attribute key="untruth-count">0</attribute>
  </attributes>
</annotation>
